infinity_llm/__init__.py
infinity_llm/client_factory.py
infinity_llm/embed/__init__.py
infinity_llm/embed/client.py
infinity_llm/embed/client_cohere.py
infinity_llm/embed/client_factory.py
infinity_llm/embed/client_mistral.py
infinity_llm/embed/client_voyage.py
infinity_llm/embedding.py
infinity_llm/notes.txt
infinity_llm/pipeline/__init__.py
infinity_llm/pipeline/api_requests.py
infinity_llm/pipeline/batch.py
infinity_llm/pipeline/process_api_requests.py
infinity_llm/pipeline/tokenize.py
infinity_llm/pipeline/utils.py
infinity_llm/utils copy.py
infinity_llm/utils.py
infinity_llm-0.1.0.dist-info/LICENSE
infinity_llm-0.1.0.dist-info/METADATA
infinity_llm-0.1.0.dist-info/WHEEL
infinity_llm-0.1.0.dist-info/RECORD
