Metadata-Version: 2.1
Name: infinity-llm
Version: 0.1.0
Summary: use any llm api in a plug-and-play fashion
License: MIT
Author: marcasty
Author-email: markacastellano2@gmail.com
Requires-Python: >=3.9,<4.0
Classifier: License :: OSI Approved :: MIT License
Classifier: Programming Language :: Python :: 3
Classifier: Programming Language :: Python :: 3.9
Classifier: Programming Language :: Python :: 3.10
Classifier: Programming Language :: Python :: 3.11
Classifier: Programming Language :: Python :: 3.12
Requires-Dist: anthropic (>=0.34.1,<0.35.0)
Requires-Dist: cohere (>=5.8.1,<6.0.0)
Requires-Dist: google-generativeai (>=0.7.2,<0.8.0)
Requires-Dist: groq (>=0.9.0,<0.10.0)
Requires-Dist: instructor (>=1.4.0,<2.0.0)
Requires-Dist: mistral-common (>=1.3.4,<2.0.0)
Requires-Dist: mistralai (>=1.0.2,<2.0.0)
Requires-Dist: openai (>=1.42.0,<2.0.0)
Requires-Dist: pydantic (==2.8.2)
Requires-Dist: tiktoken (>=0.7.0,<0.8.0)
Requires-Dist: transformers (>=4.44.2,<5.0.0)
Requires-Dist: voyageai (>=0.2.3,<0.3.0)
